chronicler/__init__.py
chronicler/_version.py
chronicler/chronicler.py
chronicler/eventizer.py
chronicler/events/core/__init__.py
chronicler/events/core/git.py
grimoirelab_chronicler-0.1.0.dist-info/METADATA
grimoirelab_chronicler-0.1.0.dist-info/WHEEL
grimoirelab_chronicler-0.1.0.dist-info/entry_points.txt
grimoirelab_chronicler-0.1.0.dist-info/licenses/AUTHORS
grimoirelab_chronicler-0.1.0.dist-info/RECORD
