Metadata-Version: 2.4
Name: grimoirelab-chronicler
Version: 0.1.0
Summary: Generator of GrimoireLab events using Perceval data.
License: GPL-3.0+
License-File: AUTHORS
Keywords: software analytics,events,grimoirelab
Author: GrimoireLab Developers
Requires-Python: >=3.11,<4.0
Classifier: Development Status :: 3 - Alpha
Classifier: Intended Audience :: Developers
Classifier: Intended Audience :: Information Technology
Classifier: Intended Audience :: Science/Research
Classifier: License :: OSI Approved :: GNU General Public License v3 or later (GPLv3+)
Classifier: Programming Language :: Python :: 3
Classifier: Programming Language :: Python :: 3.11
Classifier: Programming Language :: Python :: 3.12
Classifier: Programming Language :: Python :: 3.13
Classifier: Programming Language :: Python :: 3.14
Classifier: Topic :: Software Development
Requires-Dist: click (>=8.1.7,<9.0.0)
Requires-Dist: cloudevents (>=1.10.1,<2.0.0)
Requires-Dist: coverage (>=7.2.3,<8.0.0)
Requires-Dist: grimoirelab-toolkit (>=0.3)
Project-URL: Homepage, https://chaoss.github.io/grimoirelab/
Project-URL: Repository, https://github.com/chaoss/grimoirelab-chronicler
